conspospy/__init__.py
conspospy/conspos.py
conspospy/constants.py
conspospy/mafft.py
conspospy/pipeline.py
conspospy/utils.py
conspospy-0.1.1.dist-info/LICENSE
conspospy-0.1.1.dist-info/METADATA
conspospy-0.1.1.dist-info/WHEEL
conspospy-0.1.1.dist-info/top_level.txt
conspospy-0.1.1.dist-info/RECORD
