Metadata-Version: 2.1
Name: conspospy
Version: 0.1.1
Summary: conspospy: Python version of conspos package
Home-page: https://github.com/yamasampo/conspospy
Author: Division of Evolutionary Genetics in NIG
Author-email: hyamashita@nig.ac.jp
License: UNKNOWN
Platform: UNKNOWN
Requires-Dist: numpy
